spectrochempy/__init__.py
spectrochempy/__init__.pyi
spectrochempy/analysis/__init__.py
spectrochempy/analysis/__init__.pyi
spectrochempy/analysis/readme.rst
spectrochempy/analysis/_base/__init__.py
spectrochempy/analysis/_base/__init__.pyi
spectrochempy/analysis/_base/_analysisbase.py
spectrochempy/analysis/crossdecomposition/__init__.py
spectrochempy/analysis/crossdecomposition/__init__.pyi
spectrochempy/analysis/crossdecomposition/pls.py
spectrochempy/analysis/curvefitting/__init__.py
spectrochempy/analysis/curvefitting/__init__.pyi
spectrochempy/analysis/curvefitting/_models.py
spectrochempy/analysis/curvefitting/_parameters.py
spectrochempy/analysis/curvefitting/linearregression.py
spectrochempy/analysis/curvefitting/optimize.py
spectrochempy/analysis/decomposition/__init__.py
spectrochempy/analysis/decomposition/__init__.pyi
spectrochempy/analysis/decomposition/efa.py
spectrochempy/analysis/decomposition/fast_ica.py
spectrochempy/analysis/decomposition/iris.py
spectrochempy/analysis/decomposition/mcrals.py
spectrochempy/analysis/decomposition/nmf.py
spectrochempy/analysis/decomposition/pca.py
spectrochempy/analysis/decomposition/simplisma.py
spectrochempy/analysis/decomposition/svd.py
spectrochempy/analysis/integration/__init__.py
spectrochempy/analysis/integration/__init__.pyi
spectrochempy/analysis/integration/integrate.py
spectrochempy/analysis/kinetic/__init__.py
spectrochempy/analysis/kinetic/__init__.pyi
spectrochempy/analysis/kinetic/kineticutilities.py
spectrochempy/analysis/peakfinding/__init__.py
spectrochempy/analysis/peakfinding/__init__.pyi
spectrochempy/analysis/peakfinding/peakfinding.py
spectrochempy/application/__init__.py
spectrochempy/application/__init__.pyi
spectrochempy/application/application.py
spectrochempy/application/check_update.py
spectrochempy/application/datadir.py
spectrochempy/application/envsetup.py
spectrochempy/application/info.py
spectrochempy/application/jupyter.py
spectrochempy/application/preferences.py
spectrochempy-0.8.1.dist-info/licenses/LICENSE
spectrochempy-0.8.1.dist-info/METADATA
spectrochempy-0.8.1.dist-info/WHEEL
spectrochempy-0.8.1.dist-info/entry_points.txt
spectrochempy-0.8.1.dist-info/top_level.txt
spectrochempy-0.8.1.dist-info/RECORD
