Metadata-Version: 2.4
Name: spectrochempy
Version: 0.8.1
Summary: Processing, analysis and modelling Spectroscopic data for Chemistry with Python
Author-email: Arnaud Travert <contact@spectrochempy.fr>, Christian Fernandez <christian.fernandez@ensicaen.fr>
License: CeCILL-B FREE SOFTWARE LICENSE AGREEMENT
Project-URL: documentation, https://www.spectrochempy.fr/latest
Project-URL: homepage, https://www.spectrochempy.fr
Project-URL: issues, https://github.com/spectrochempy/spectrochempy/issues
Project-URL: repository, https://github.com/spectrochempy/spectrochempy
Keywords: spectroscopy,chemistry,data analysis
Classifier: Development Status :: 3 - Alpha
Classifier: Topic :: Utilities
Classifier: Topic :: Scientific/Engineering
Classifier: Topic :: Software Development :: Libraries
Classifier: Intended Audience :: Science/Research
Classifier: License :: CeCILL-B Free Software License Agreement (CECILL-B)
Classifier: Operating System :: OS Independent
Classifier: Programming Language :: Python :: 3.10
Classifier: Programming Language :: Python :: 3.11
Classifier: Programming Language :: Python :: 3.12
Classifier: Programming Language :: Python :: 3.13
Requires-Python: >=3.10
License-File: LICENSE
Requires-Dist: colorama
Requires-Dist: dill
Requires-Dist: docrep
Requires-Dist: ipython
Requires-Dist: jinja2
Requires-Dist: lazy_loader
Requires-Dist: matplotlib
Requires-Dist: numpy
Requires-Dist: numpydoc
Requires-Dist: numpy-quaternion>=2024.0.7
Requires-Dist: osqp
Requires-Dist: pint
Requires-Dist: pyyaml
Requires-Dist: requests
Requires-Dist: scikit-learn
Requires-Dist: scipy
Requires-Dist: setuptools-scm
Requires-Dist: tzlocal
Requires-Dist: xlrd
Provides-Extra: build
Requires-Dist: setuptools; extra == "build"
Requires-Dist: setuptools_scm; extra == "build"
Requires-Dist: toml; extra == "build"
Requires-Dist: jinja2; extra == "build"
Requires-Dist: anaconda-client; extra == "build"
Provides-Extra: cantera
Requires-Dist: cantera; extra == "cantera"
Provides-Extra: dev
Requires-Dist: toml; extra == "dev"
Requires-Dist: ruff; extra == "dev"
Requires-Dist: pre-commit; extra == "dev"
Requires-Dist: spectrochempy[interactive]; extra == "dev"
Requires-Dist: spectrochempy[test]; extra == "dev"
Requires-Dist: spectrochempy[docs]; extra == "dev"
Provides-Extra: docs
Requires-Dist: ipykernel==6.29.5; extra == "docs"
Requires-Dist: ipywidgets==8.1.5; extra == "docs"
Requires-Dist: jsonschema==4.23.0; extra == "docs"
Requires-Dist: jupyter==1.1.1; extra == "docs"
Requires-Dist: jupyter-sphinx; extra == "docs"
Requires-Dist: jupytext==1.16.7; extra == "docs"
Requires-Dist: nbconvert==7.16.6; extra == "docs"
Requires-Dist: nbformat==5.10.4; extra == "docs"
Requires-Dist: nbsphinx==0.9.6; extra == "docs"
Requires-Dist: numpydoc==1.8.0; extra == "docs"
Requires-Dist: pickleshare; extra == "docs"
Requires-Dist: pypandoc==1.15; extra == "docs"
Requires-Dist: sphinx==7.4.7; extra == "docs"
Requires-Dist: sphinx-tabs==3.4.7; extra == "docs"
Requires-Dist: sphinx-copybutton==0.5.2; extra == "docs"
Requires-Dist: sphinx-design==0.6.0; extra == "docs"
Requires-Dist: sphinx-gallery==0.19.0; extra == "docs"
Requires-Dist: sphinx-rtd-theme==3.0.2; extra == "docs"
Requires-Dist: sphinxcontrib-bibtex==2.6.3; extra == "docs"
Requires-Dist: json5==0.10.0; extra == "docs"
Provides-Extra: interactive
Requires-Dist: jupyter; extra == "interactive"
Requires-Dist: jupyterlab; extra == "interactive"
Requires-Dist: ipykernel; extra == "interactive"
Requires-Dist: ipyparallel; extra == "interactive"
Requires-Dist: nodejs; extra == "interactive"
Requires-Dist: jupyter_server; extra == "interactive"
Provides-Extra: test
Requires-Dist: coverage; extra == "test"
Requires-Dist: ipywidgets; extra == "test"
Requires-Dist: pyfakefs; extra == "test"
Requires-Dist: pytest; extra == "test"
Requires-Dist: pytest-cov; extra == "test"
Requires-Dist: pytest-doctestplus; extra == "test"
Requires-Dist: pytest-ruff; extra == "test"
Requires-Dist: pytest-mock; extra == "test"
Requires-Dist: numpydoc; extra == "test"
Dynamic: license-file
